libpythonpro/__init__.py
libpythonpro/github_api.py
libpythonpro/__pycache__/__init__.cpython-39.pyc
libpythonpro/spam/__init__.py
libpythonpro/spam/db.py
libpythonpro/spam/enviador_de_email.py
libpythonpro/spam/main.py
libpythonpro/spam/modelos.py
libpythonpro/tests/__init__.py
libpythonpro/tests/test_exemplo.py
libpythonpro/tests/__pycache__/__init__.cpython-39.pyc
libpythonpro/tests/test_spam/__init__.py
libpythonpro/tests/test_spam/conftest.py
libpythonpro/tests/test_spam/test_enviador_de_email.py
libpythonpro/tests/test_spam/test_envio_para_base_de_usuarios.py
libpythonpro/tests/test_spam/test_github_api.py
libpythonpro/tests/test_spam/test_usuarios.py
libpythonpro_r-0.4.dist-info/LICENSE
libpythonpro_r-0.4.dist-info/METADATA
libpythonpro_r-0.4.dist-info/WHEEL
libpythonpro_r-0.4.dist-info/top_level.txt
libpythonpro_r-0.4.dist-info/RECORD
