Metadata-Version: 2.1
Name: libpythonpro-r
Version: 0.4
Summary: Módulo para exemplificar construção de projetos Python no curso PyTools
Home-page: https://github.com/ricardovezetiv/libpythonpro
Author: Ricardo Vezetiv
Author-email: ricardo.vezetiv@mail.ru
License: GNU AFFERO GENERAL PUBLIC LICENSE
Platform: UNKNOWN
Classifier: Development Status :: 2 - Pre-Alpha
Classifier: Environment :: Console
Classifier: Intended Audience :: Developers
Classifier: License :: OSI Approved :: GNU Affero General Public License v3 or later (AGPLv3+)
Classifier: Operating System :: OS Independent
Classifier: Programming Language :: Python
Classifier: Programming Language :: Python :: 3.9
Classifier: Framework :: Pytest
License-File: LICENSE
Requires-Dist: requests
